jec_api/__init__.py
jec_api/core.py
jec_api/decorators.py
jec_api/discovery.py
jec_api/route.py
jec_api/dev/__init__.py
jec_api/dev/dev_console.py
jec_api/dev/dev_endpoint_tester.py
jec_api-0.0.7.dist-info/METADATA
jec_api-0.0.7.dist-info/WHEEL
jec_api-0.0.7.dist-info/licenses/LICENSE
jec_api-0.0.7.dist-info/RECORD
