Metadata-Version: 2.4
Name: jec-api
Version: 0.0.7
Summary: Just Encapsulated Controllers — The Class-Based System for Application Program Interfaces
Project-URL: Homepage, https://github.com/alpheay/jec
Project-URL: Repository, https://github.com/alpheay/jec
Author: nik
License-Expression: MIT
License-File: LICENSE
Keywords: api,class-based,fastapi,routes,web
Classifier: Development Status :: 4 - Beta
Classifier: Framework :: FastAPI
Classifier: Intended Audience :: Developers
Classifier: License :: OSI Approved :: MIT License
Classifier: Programming Language :: Python :: 3
Classifier: Programming Language :: Python :: 3.9
Classifier: Programming Language :: Python :: 3.10
Classifier: Programming Language :: Python :: 3.11
Classifier: Programming Language :: Python :: 3.12
Classifier: Topic :: Internet :: WWW/HTTP :: HTTP Servers
Requires-Python: >=3.9
Requires-Dist: fastapi>=0.100.0
Provides-Extra: dev
Requires-Dist: httpx>=0.24.0; extra == 'dev'
Requires-Dist: pytest>=7.0.0; extra == 'dev'
Requires-Dist: uvicorn>=0.20.0; extra == 'dev'
